cruscopoetry/syllabifiers/swa/__init__.py
cruscopoetry/syllabifiers/swa/__main__.py
cruscopoetry/syllabifiers/swa/syllabifier.py
cruscopoetry/syllabifiers/swa/syllable.py
cruscopoetry/syllabifiers/swa/tokenizer.py
cruscopoetry.syllabifiers.swa-0.0.2.dist-info/METADATA
cruscopoetry.syllabifiers.swa-0.0.2.dist-info/WHEEL
cruscopoetry.syllabifiers.swa-0.0.2.dist-info/top_level.txt
cruscopoetry.syllabifiers.swa-0.0.2.dist-info/RECORD
