Metadata-Version: 2.1
Name: cruscopoetry.syllabifiers.swa
Version: 0.0.2
Summary: Syllabifier for poems in CruscoPoetry format in Swahili language
Home-page: https://gitlab.com/kikulacho92/cruscopoetry
Author: Emiliano Minerba
Author-email: emi.nerba@gmail.com
License: GPL
Platform: UNKNOWN
Requires-Dist: cruscopoetry.syllabifiers.abstract (==0.0.2)
